patchy/__init__.py
patchy/api.py
patchy/cache.py
patchy/py.typed
patchy-2.10.0.dist-info/licenses/LICENSE
patchy-2.10.0.dist-info/METADATA
patchy-2.10.0.dist-info/WHEEL
patchy-2.10.0.dist-info/top_level.txt
patchy-2.10.0.dist-info/RECORD
